holistics_dbt/__init__.py
holistics_dbt/aml_dimension.py
holistics_dbt/aml_gen.py
holistics_dbt/aml_table_model.py
holistics_dbt/dbt.py
holistics_dbt/databases/__init__.py
holistics_dbt/databases/base_database.py
holistics_dbt/databases/bigquery.py
holistics_dbt-0.0.2.dist-info/METADATA
holistics_dbt-0.0.2.dist-info/WHEEL
holistics_dbt-0.0.2.dist-info/top_level.txt
holistics_dbt-0.0.2.dist-info/RECORD
