Metadata-Version: 2.1
Name: holistics-dbt
Version: 0.0.2
Summary: Holistics DBT utilities
Author-email: Holistics <support@holistics.io>
Maintainer-email: Holistics <support@holistics.io>
Project-URL: Repository, https://github.com/holistics/holistics_dbt.git
Project-URL: Homepage, https://github.com/holistics/holistics_dbt.git
Requires-Python: >=3.8
